pybmda/__init__.py
pybmda/bmda.py
pybmda/utils.py
pybmda-0.2.5.dist-info/LICENSE
pybmda-0.2.5.dist-info/METADATA
pybmda-0.2.5.dist-info/WHEEL
pybmda-0.2.5.dist-info/top_level.txt
pybmda-0.2.5.dist-info/RECORD
