Metadata-Version: 2.1
Name: pybmda
Version: 0.2.5
Summary: Python interface for BlackMagicDebugApplication (BMDA)
Home-page: https://github.com/Lynkz-Instruments/pybmda
Author: Lynkz Instruments Inc
Author-email: xavier@lynkz.ca
License: MIT
Classifier: Development Status :: 3 - Alpha
Classifier: Intended Audience :: Developers
Classifier: Operating System :: POSIX :: Linux
Classifier: Operating System :: Unix
License-File: LICENSE
